Workbook

Sheet Income Statement
A1: Line Item | B1: FY 2021 | C1: FY 2022 | D1: FY 2023 | E1: FY 2024 | F1: FY 2025
A2: Revenue from Operations | B2: 20602 | C2: 27210 | D2: 38270 | E2: 47114 | F2: 54842
A3: Other Income | B3: 181 | C3: 246 | D3: 299 | E3: 510 | F3: 493
A4: Total Income | B4: 20783 | C4: 27456 | D4: 38569 | E4: 47624 | F4: 55335
A6: Cost of Materials Consumed | B6: 13143 | C6: 20939 | D6: 25085 | E6: 33556 | F6: 43905
A7: Purchases of Stock-in-Trade | B7: 2462 | C7: 4187 | D7: 5438 | E7: 5535 | F7: 6372
A8: Changes in Inventories | B8: 164 | C8: -4468 | D8: -1477 | E8: -2149 | F8: -6537
A9: Employee Benefits Expense | B9: 911 | C9: 1143 | D9: 1362 | E9: 1503 | F9: 1717
A10: Finance Costs | B10: 181 | C10: 195 | D10: 240 | E10: 480 | F10: 767
A11: Depreciation & Amortization | B11: 331 | C11: 347 | D11: 364 | E11: 447 | F11: 537
A12: Other Expenses | B12: 2221 | C12: 2130 | D12: 3092 | E12: 3645 | F12: 4093
A13: Total Expenses | B13: =SUM(B6:B12) -> 19413 | C13: =SUM(C6:C12) -> 24473 | D13: =SUM(D6:D12) -> 34104 | E13: =SUM(E6:E12) -> 43017 | F13: =SUM(F6:F12) -> 50854
A15: Profit Before Tax | B15: 1233 | C15: 2932 | D15: 4465 | E15: 4607 | F15: 4481
A16: Tax Expense | B16: 356 | C16: 752 | D16: 1132 | E16: 1063 | F16: 1146
A17: Profit After Tax | B17: =B15-B16 -> 877 | C17: =C15-C16 -> 2180 | D17: =D15-D16 -> 3333 | E17: =E15-E16 -> 3544 | F17: =F15-F16 -> 3335

Sheet Balance Sheet
A1: Line Item | B1: FY 2021 | C1: FY 2022 | D1: FY 2023 | E1: FY 2024 | F1: FY 2025
A2: ASSETS
A3: Non-Current Assets | B3: 3359 | C3: 3758 | D3: 4402 | E3: 10169 | F3: 10631
A4: Current Assets | B4: 12501 | C4: 16379 | D4: 20686 | E4: 22693 | F4: 30444
A5: Total Assets | B5: =SUM(B3:B4) -> 15860 | C5: =SUM(C3:C4) -> 20137 | D5: =SUM(D3:D4) -> 25088 | E5: =SUM(E3:E4) -> 32862 | F5: =SUM(F3:F4) -> 41075
A7: EQUITY & LIABILITIES
A8: Equity Share Capital | B8: 89 | C8: 89 | D8: 89 | E8: 89 | F8: 89
A9: Other Equity | B9: 7464 | C9: 9284 | D9: 11905 | E9: 14368 | F9: 16722
A10: Total Equity | B10: =SUM(B8:B9) -> 7553 | C10: =SUM(C8:C9) -> 9373 | D10: =SUM(D8:D9) -> 11994 | E10: =SUM(E8:E9) -> 14457 | F10: =SUM(F8:F9) -> 16811
A11: Non-Current Liabilities | B11: 1114 | C11: 1205 | D11: 1573 | E11: 5043 | F11: 2619
A12: Current Liabilities | B12: 7193 | C12: 9559 | D12: 11521 | E12: 13362 | F12: 21645
A13: Total Liabilities | B13: =SUM(B11:B12) -> 8307 | C13: =SUM(C11:C12) -> 10764 | D13: =SUM(D11:D12) -> 13094 | E13: =SUM(E11:E12) -> 18405 | F13: =SUM(F11:F12) -> 24264
A14: Total Equity & Liabilities | B14: =B10+B13 -> 15860 | C14: =C10+C13 -> 20137 | D14: =D10+D13 -> 25088 | E14: =E10+E13 -> 32862 | F14: =F10+F13 -> 41075

Sheet Cash Flow
A1: Line Item | B1: FY 2021 | C1: FY 2022 | D1: FY 2023 | E1: FY 2024 | F1: FY 2025
A2: Cash Flow from Operating Activities | B2: 4101 | C2: -1126 | D2: 1810 | E2: 2030 | F2: -170
A3: Cash Flow from Investing Activities | B3: -2744 | C3: 1564 | D3: -1653 | E3: -4634 | F3: 140
A4: Cash Flow from Financing Activities | B4: -1260 | C4: -468 | D4: -155 | E4: 2757 | F4: 1
A5: Net Increase/Decrease in Cash | B5: 97 | C5: -30 | D5: 2 | E5: 153 | F5: -29
A6: Opening Cash & Cash Equivalents | B6: 50 | C6: 147 | D6: 117 | E6: 119 | F6: 272
A7: Closing Cash & Cash Equivalents | B7: 147 | C7: 117 | D7: 119 | E7: 272 | F7: 243

Sheet Ratios
A1: Ratio | B1: FY 2021 | C1: FY 2022 | D1: FY 2023 | E1: FY 2024 | F1: FY 2025
A2: Revenue Growth(%) | C2: =('Income Statement'!C2-'Income Statement'!B2)/'Income Statement'!B2 -> 0.32074556 | D2: =('Income Statement'!D2-'Income Statement'!C2)/'Income Statement'!C2 -> 0.40646821 | E2: =('Income Statement'!E2-'Income Statement'!D2)/'Income Statement'!D2 -> 0.23109485 | F2: =('Income Statement'!F2-'Income Statement'!E2)/'Income Statement'!E2 -> 0.16402768
A3: Net Profit Margin(%) | C3: ='Income Statement'!B17/'Income Statement'!B2 -> 0.042568683 | D3: ='Income Statement'!C17/'Income Statement'!C2 -> 0.080117604 | E3: ='Income Statement'!D17/'Income Statement'!D2 -> 0.087091717 | F3: ='Income Statement'!E17/'Income Statement'!E2 -> 0.075221802
A4: Return on Equity | C4: ='Income Statement'!B17/'Balance Sheet'!B10 -> 0.1161128 | D4: ='Income Statement'!C17/'Balance Sheet'!C10 -> 0.23258295 | E4: ='Income Statement'!D17/'Balance Sheet'!D10 -> 0.27788894 | F4: ='Income Statement'!E17/'Balance Sheet'!E10 -> 0.24514076
A5: Return on Assets | C5: ='Income Statement'!B17/'Balance Sheet'!B5 -> 0.055296343 | D5: ='Income Statement'!C17/'Balance Sheet'!C5 -> 0.10825843 | E5: ='Income Statement'!D17/'Balance Sheet'!D5 -> 0.13285236 | F5: ='Income Statement'!E17/'Balance Sheet'!E5 -> 0.10784493
A6: Current Ratio | C6: ='Balance Sheet'!B4/'Balance Sheet'!B12 -> 1.7379397 | D6: ='Balance Sheet'!C4/'Balance Sheet'!C12 -> 1.7134638 | E6: ='Balance Sheet'!D4/'Balance Sheet'!D12 -> 1.7955039 | F6: ='Balance Sheet'!E4/'Balance Sheet'!E12 -> 1.6983236
A7: Debt-to-Equity Ratio | C7: =('Balance Sheet'!B11+'Balance Sheet'!B12)/'Balance Sheet'!B10 -> 1.0998279 | D7: =('Balance Sheet'!C11+'Balance Sheet'!C12)/'Balance Sheet'!C10 -> 1.148405 | E7: =('Balance Sheet'!D11+'Balance Sheet'!D12)/'Balance Sheet'!D10 -> 1.0917125 | F7: =('Balance Sheet'!E11+'Balance Sheet'!E12)/'Balance Sheet'!E10 -> 1.2730857

Sheet Charts

Sheet Insights
A1: Key Financial Insights (FY2021–FY2025)
A2: Revenue Trend | B2: Revenue increased from ₹20,602 crore in FY2021 to ₹54,842 crore in FY2025, representing strong and consistent business growth.
A3: Profitability | B3: Profit after tax increased significantly from ₹877 crore to ₹3,335 crore over five years, indicating improved profitability despite a slight decline in FY2025.
A4: Expenses | B4: Total expenses increased alongside revenue, but revenue grew at a faster pace, helping maintain healthy profit margins.
A5: Assets | B5: Total assets increased steadily from ₹15,860 crore to ₹41,075 crore, reflecting continuous expansion of the company's operations.
A6: Liabilities | B6: Liabilities increased over the years, but shareholder equity also grew, indicating balanced financing rather than excessive debt dependence. | E6: ``
A7: Cash Flow | B7: Operating cash flow remained positive in most years, while investing cash flow was largely negative due to continued investments in business growth.
A8: ROE & ROA | B8: Return on Equity and Return on Assets improved substantially compared to FY2021, indicating more efficient utilization of shareholder funds and company assets.
A9: Overall Assessment | B9: Titan demonstrated strong revenue growth, expanding assets, improving profitability, and consistent long-term business performance. Although FY2025 showed slightly lower profits and operating cash flow, the company's overall financial position remains strong.
